bot_lib/__init__.py
bot_lib/bot_lib.py
bot_lib_public-2.0.0.dist-info/LICENSE
bot_lib_public-2.0.0.dist-info/METADATA
bot_lib_public-2.0.0.dist-info/WHEEL
bot_lib_public-2.0.0.dist-info/top_level.txt
bot_lib_public-2.0.0.dist-info/RECORD
