Metadata-Version: 2.1
Name: bot-lib-public
Version: 2.0.0
Summary: Wrapper for Selenium and contains supporting classes for browser automation
Home-page: https://github.com/fahim-programmer/bot-lib-public/
Author: Fahim Chohan
License: Apache-2.0 license
Platform: Windows
Platform: MacOS
Platform: Linux
Classifier: License :: OSI Approved :: Apache Software License
Classifier: Natural Language :: English
Classifier: Development Status :: 3 - Alpha
Classifier: Programming Language :: Python :: 3
Classifier: Programming Language :: Python :: 3.9
Classifier: Operating System :: POSIX :: Linux
Classifier: Operating System :: MacOS :: MacOS X
Classifier: Operating System :: Microsoft :: Windows
Requires-Dist: selenium (==4.8.0)
Requires-Dist: requests (==2.27.0)
Requires-Dist: Pillow (==10.0.0)
Requires-Dist: PySocks (==1.7.1)
Requires-Dist: numpy (==1.25.1)
